{
  "functions": [
    {
      "complexity": 0,
      "file_name": "documentation_agent.py",
      "function_name": "DocumentationAgent::_create_error_result",
      "path": "documentation_agent.py"
    },
    {
      "complexity": 0,
      "file_name": "documentation_agent.py",
      "function_name": "DocumentationAgent::_create_initial_changelog",
      "path": "documentation_agent.py"
    },
    {
      "complexity": 0,
      "file_name": "documentation_agent.py",
      "function_name": "DocumentationAgent::_fix_agent_count_references",
      "path": "documentation_agent.py"
    },
    {
      "complexity": 0,
      "file_name": "documentation_agent.py",
      "function_name": "DocumentationAgent::_general_documentation_update",
      "path": "documentation_agent.py"
    },
    {
      "complexity": 0,
      "file_name": "documentation_agent.py",
      "function_name": "DocumentationAgent::_generate_changelog_entry",
      "path": "documentation_agent.py"
    },
    {
      "complexity": 0,
      "file_name": "documentation_agent.py",
      "function_name": "DocumentationAgent::_get_agent_count_patterns",
      "path": "documentation_agent.py"
    },
    {
      "complexity": 0,
      "file_name": "documentation_agent.py",
      "function_name": "DocumentationAgent::_get_safe_pattern_map",
      "path": "documentation_agent.py"
    },
    {
      "complexity": 0,
      "file_name": "documentation_agent.py",
      "function_name": "DocumentationAgent::_read_file_content",
      "path": "documentation_agent.py"
    },
    {
      "complexity": 0,
      "file_name": "documentation_agent.py",
      "function_name": "DocumentationAgent::get_supported_types",
      "path": "documentation_agent.py"
    },
    {
      "complexity": 1,
      "file_name": "documentation_agent.py",
      "function_name": "DocumentationAgent::_add_section_to_entry",
      "path": "documentation_agent.py"
    },
    {
      "complexity": 1,
      "file_name": "documentation_agent.py",
      "function_name": "DocumentationAgent::_categorize_changes",
      "path": "documentation_agent.py"
    },
    {
      "complexity": 1,
      "file_name": "documentation_agent.py",
      "function_name": "DocumentationAgent::_create_success_message",
      "path": "documentation_agent.py"
    },
    {
      "complexity": 1,
      "file_name": "documentation_agent.py",
      "function_name": "DocumentationAgent::_get_commit_messages",
      "path": "documentation_agent.py"
    },
    {
      "complexity": 1,
      "file_name": "documentation_agent.py",
      "function_name": "DocumentationAgent::_get_commit_range",
      "path": "documentation_agent.py"
    },
    {
      "complexity": 1,
      "file_name": "documentation_agent.py",
      "function_name": "DocumentationAgent::_is_count_mismatch",
      "path": "documentation_agent.py"
    },
    {
      "complexity": 1,
      "file_name": "documentation_agent.py",
      "function_name": "DocumentationAgent::_write_fixed_content",
      "path": "documentation_agent.py"
    },
    {
      "complexity": 1,
      "file_name": "documentation_agent.py",
      "function_name": "DocumentationAgent::can_handle",
      "path": "documentation_agent.py"
    },
    {
      "complexity": 2,
      "file_name": "documentation_agent.py",
      "function_name": "DocumentationAgent::_check_file_agent_count",
      "path": "documentation_agent.py"
    },
    {
      "complexity": 2,
      "file_name": "documentation_agent.py",
      "function_name": "DocumentationAgent::_check_pattern_for_count_mismatch",
      "path": "documentation_agent.py"
    },
    {
      "complexity": 2,
      "file_name": "documentation_agent.py",
      "function_name": "DocumentationAgent::_fix_broken_link",
      "path": "documentation_agent.py"
    },
    {
      "complexity": 3,
      "file_name": "documentation_agent.py",
      "function_name": "DocumentationAgent::_add_categorized_changes_to_entry",
      "path": "documentation_agent.py"
    },
    {
      "complexity": 3,
      "file_name": "documentation_agent.py",
      "function_name": "DocumentationAgent::_analyze_file_content_for_agent_count",
      "path": "documentation_agent.py"
    },
    {
      "complexity": 3,
      "file_name": "documentation_agent.py",
      "function_name": "DocumentationAgent::_attempt_link_fix",
      "path": "documentation_agent.py"
    },
    {
      "complexity": 3,
      "file_name": "documentation_agent.py",
      "function_name": "DocumentationAgent::_check_agent_count_consistency",
      "path": "documentation_agent.py"
    },
    {
      "complexity": 3,
      "file_name": "documentation_agent.py",
      "function_name": "DocumentationAgent::_extract_target_file_from_details",
      "path": "documentation_agent.py"
    },
    {
      "complexity": 3,
      "file_name": "documentation_agent.py",
      "function_name": "DocumentationAgent::_find_and_fix_link",
      "path": "documentation_agent.py"
    },
    {
      "complexity": 3,
      "file_name": "documentation_agent.py",
      "function_name": "DocumentationAgent::_find_count_mismatch_in_matches",
      "path": "documentation_agent.py"
    },
    {
      "complexity": 3,
      "file_name": "documentation_agent.py",
      "function_name": "DocumentationAgent::_get_change_category",
      "path": "documentation_agent.py"
    },
    {
      "complexity": 3,
      "file_name": "documentation_agent.py",
      "function_name": "DocumentationAgent::_get_recent_changes",
      "path": "documentation_agent.py"
    },
    {
      "complexity": 4,
      "file_name": "documentation_agent.py",
      "function_name": "DocumentationAgent::_insert_changelog_entry",
      "path": "documentation_agent.py"
    },
    {
      "complexity": 6,
      "file_name": "documentation_agent.py",
      "function_name": "DocumentationAgent::_update_changelog",
      "path": "documentation_agent.py"
    },
    {
      "complexity": 7,
      "file_name": "documentation_agent.py",
      "function_name": "DocumentationAgent::_fix_or_remove_broken_link_line",
      "path": "documentation_agent.py"
    },
    {
      "complexity": 8,
      "file_name": "documentation_agent.py",
      "function_name": "DocumentationAgent::_update_readme_examples",
      "path": "documentation_agent.py"
    },
    {
      "complexity": 9,
      "file_name": "documentation_agent.py",
      "function_name": "DocumentationAgent::_update_api_documentation",
      "path": "documentation_agent.py"
    },
    {
      "complexity": 10,
      "file_name": "documentation_agent.py",
      "function_name": "DocumentationAgent::_detect_api_changes",
      "path": "documentation_agent.py"
    },
    {
      "complexity": 10,
      "file_name": "documentation_agent.py",
      "function_name": "DocumentationAgent::_parse_commit_messages",
      "path": "documentation_agent.py"
    },
    {
      "complexity": 11,
      "file_name": "documentation_agent.py",
      "function_name": "DocumentationAgent::_fix_documentation_consistency",
      "path": "documentation_agent.py"
    },
    {
      "complexity": 12,
      "file_name": "documentation_agent.py",
      "function_name": "DocumentationAgent::analyze_and_fix",
      "path": "documentation_agent.py"
    },
    {
      "complexity": 0,
      "file_name": "autofix_coordinator.py",
      "function_name": "AutofixCoordinator::_build_check_commands",
      "path": "autofix_coordinator.py"
    },
    {
      "complexity": 0,
      "file_name": "autofix_coordinator.py",
      "function_name": "AutofixCoordinator::_check_string_result_success",
      "path": "autofix_coordinator.py"
    },
    {
      "complexity": 0,
      "file_name": "autofix_coordinator.py",
      "function_name": "AutofixCoordinator::_get_convergence_threshold",
      "path": "autofix_coordinator.py"
    },
    {
      "complexity": 0,
      "file_name": "autofix_coordinator.py",
      "function_name": "AutofixCoordinator::_log_hook_parsing_result",
      "path": "autofix_coordinator.py"
    },
    {
      "complexity": 0,
      "file_name": "autofix_coordinator.py",
      "function_name": "AutofixCoordinator::_report_iteration_success",
      "path": "autofix_coordinator.py"
    },
    {
      "complexity": 0,
      "file_name": "autofix_coordinator.py",
      "function_name": "AutofixCoordinator::apply_comprehensive_stage_fixes",
      "path": "autofix_coordinator.py"
    },
    {
      "complexity": 0,
      "file_name": "autofix_coordinator.py",
      "function_name": "AutofixCoordinator::apply_fast_stage_fixes",
      "path": "autofix_coordinator.py"
    },
    {
      "complexity": 0,
      "file_name": "autofix_coordinator.py",
      "function_name": "AutofixCoordinator::check_tool_success_patterns",
      "path": "autofix_coordinator.py"
    },
    {
      "complexity": 0,
      "file_name": "autofix_coordinator.py",
      "function_name": "AutofixCoordinator::run_fix_command",
      "path": "autofix_coordinator.py"
    },
    {
      "complexity": 0,
      "file_name": "autofix_coordinator.py",
      "function_name": "AutofixCoordinator::should_skip_autofix",
      "path": "autofix_coordinator.py"
    },
    {
      "complexity": 0,
      "file_name": "autofix_coordinator.py",
      "function_name": "AutofixCoordinator::validate_fix_command",
      "path": "autofix_coordinator.py"
    },
    {
      "complexity": 0,
      "file_name": "autofix_coordinator.py",
      "function_name": "AutofixCoordinator::validate_hook_result",
      "path": "autofix_coordinator.py"
    },
    {
      "complexity": 1,
      "file_name": "autofix_coordinator.py",
      "function_name": "AutofixCoordinator::_check_process_result_success",
      "path": "autofix_coordinator.py"
    },
    {
      "complexity": 1,
      "file_name": "autofix_coordinator.py",
      "function_name": "AutofixCoordinator::_create_link_error_details",
      "path": "autofix_coordinator.py"
    },
    {
      "complexity": 1,
      "file_name": "autofix_coordinator.py",
      "function_name": "AutofixCoordinator::_create_link_error_message",
      "path": "autofix_coordinator.py"
    },
    {
      "complexity": 1,
      "file_name": "autofix_coordinator.py",
      "function_name": "AutofixCoordinator::_extract_target_file_from_message",
      "path": "autofix_coordinator.py"
    },
    {
      "complexity": 1,
      "file_name": "autofix_coordinator.py",
      "function_name": "AutofixCoordinator::_format_codespell_message",
      "path": "autofix_coordinator.py"
    },
    {
      "complexity": 1,
      "file_name": "autofix_coordinator.py",
      "function_name": "AutofixCoordinator::_get_hook_specific_fixes",
      "path": "autofix_coordinator.py"
    },
    {
      "complexity": 1,
      "file_name": "autofix_coordinator.py",
      "function_name": "AutofixCoordinator::_get_iteration_issues",
      "path": "autofix_coordinator.py"
    },
    {
      "complexity": 1,
      "file_name": "autofix_coordinator.py",
      "function_name": "AutofixCoordinator::_get_max_iterations",
      "path": "autofix_coordinator.py"
    },
    {
      "complexity": 1,
      "file_name": "autofix_coordinator.py",
      "function_name": "AutofixCoordinator::_has_success_patterns",
      "path": "autofix_coordinator.py"
    },
    {
      "complexity": 1,
      "file_name": "autofix_coordinator.py",
      "function_name": "AutofixCoordinator::_parse_line_number",
      "path": "autofix_coordinator.py"
    },
    {
      "complexity": 1,
      "file_name": "autofix_coordinator.py",
      "function_name": "AutofixCoordinator::_report_iteration_progress",
      "path": "autofix_coordinator.py"
    },
    {
      "complexity": 1,
      "file_name": "autofix_coordinator.py",
      "function_name": "AutofixCoordinator::_report_max_iterations_reached",
      "path": "autofix_coordinator.py"
    },
    {
      "complexity": 1,
      "file_name": "autofix_coordinator.py",
      "function_name": "AutofixCoordinator::_run_ai_fix_iteration",
      "path": "autofix_coordinator.py"
    },
    {
      "complexity": 1,
      "file_name": "autofix_coordinator.py",
      "function_name": "AutofixCoordinator::_should_parse_codespell_line",
      "path": "autofix_coordinator.py"
    },
    {
      "complexity": 1,
      "file_name": "autofix_coordinator.py",
      "function_name": "AutofixCoordinator::_should_parse_local_link_line",
      "path": "autofix_coordinator.py"
    },
    {
      "complexity": 1,
      "file_name": "autofix_coordinator.py",
      "function_name": "AutofixCoordinator::_update_progress_count",
      "path": "autofix_coordinator.py"
    },
    {
      "complexity": 2,
      "file_name": "autofix_coordinator.py",
      "function_name": "AutofixCoordinator::_apply_fast_stage_fixes",
      "path": "autofix_coordinator.py"
    },
    {
      "complexity": 2,
      "file_name": "autofix_coordinator.py",
      "function_name": "AutofixCoordinator::_collect_current_issues",
      "path": "autofix_coordinator.py"
    },
    {
      "complexity": 2,
      "file_name": "autofix_coordinator.py",
      "function_name": "AutofixCoordinator::_execute_ai_fix",
      "path": "autofix_coordinator.py"
    },
    {
      "complexity": 2,
      "file_name": "autofix_coordinator.py",
      "function_name": "AutofixCoordinator::_extract_codespell_parts",
      "path": "autofix_coordinator.py"
    },
    {
      "complexity": 2,
      "file_name": "autofix_coordinator.py",
      "function_name": "AutofixCoordinator::_extract_local_link_parts",
      "path": "autofix_coordinator.py"
    },
    {
      "complexity": 2,
      "file_name": "autofix_coordinator.py",
      "function_name": "AutofixCoordinator::_extract_message",
      "path": "autofix_coordinator.py"
    },
    {
      "complexity": 2,
      "file_name": "autofix_coordinator.py",
      "function_name": "AutofixCoordinator::_get_ruff_severity",
      "path": "autofix_coordinator.py"
    },
    {
      "complexity": 2,
      "file_name": "autofix_coordinator.py",
      "function_name": "AutofixCoordinator::_handle_partial_progress",
      "path": "autofix_coordinator.py"
    },
    {
      "complexity": 2,
      "file_name": "autofix_coordinator.py",
      "function_name": "AutofixCoordinator::_has_import_errors",
      "path": "autofix_coordinator.py"
    },
    {
      "complexity": 2,
      "file_name": "autofix_coordinator.py",
      "function_name": "AutofixCoordinator::_kill_process_gracefully",
      "path": "autofix_coordinator.py"
    },
    {
      "complexity": 2,
      "file_name": "autofix_coordinator.py",
      "function_name": "AutofixCoordinator::_parse_generic_output",
      "path": "autofix_coordinator.py"
    },
    {
      "complexity": 2,
      "file_name": "autofix_coordinator.py",
      "function_name": "AutofixCoordinator::_parse_type_checker_line",
      "path": "autofix_coordinator.py"
    },
    {
      "complexity": 2,
      "file_name": "autofix_coordinator.py",
      "function_name": "AutofixCoordinator::_run_check_command",
      "path": "autofix_coordinator.py"
    },
    {
      "complexity": 2,
      "file_name": "autofix_coordinator.py",
      "function_name": "AutofixCoordinator::_run_fix_command",
      "path": "autofix_coordinator.py"
    },
    {
      "complexity": 3,
      "file_name": "autofix_coordinator.py",
      "function_name": "AutofixCoordinator::__init__",
      "path": "autofix_coordinator.py"
    },
    {
      "complexity": 3,
      "file_name": "autofix_coordinator.py",
      "function_name": "AutofixCoordinator::_check_tool_success_patterns",
      "path": "autofix_coordinator.py"
    },
    {
      "complexity": 3,
      "file_name": "autofix_coordinator.py",
      "function_name": "AutofixCoordinator::_execute_check_commands",
      "path": "autofix_coordinator.py"
    },
    {
      "complexity": 3,
      "file_name": "autofix_coordinator.py",
      "function_name": "AutofixCoordinator::_execute_fast_fixes",
      "path": "autofix_coordinator.py"
    },
    {
      "complexity": 3,
      "file_name": "autofix_coordinator.py",
      "function_name": "AutofixCoordinator::_extract_raw_output",
      "path": "autofix_coordinator.py"
    },
    {
      "complexity": 3,
      "file_name": "autofix_coordinator.py",
      "function_name": "AutofixCoordinator::_handle_command_result",
      "path": "autofix_coordinator.py"
    },
    {
      "complexity": 3,
      "file_name": "autofix_coordinator.py",
      "function_name": "AutofixCoordinator::_log_hook_parsing_start",
      "path": "autofix_coordinator.py"
    },
    {
      "complexity": 3,
      "file_name": "autofix_coordinator.py",
      "function_name": "AutofixCoordinator::_parse_single_codespell_line",
      "path": "autofix_coordinator.py"
    },
    {
      "complexity": 3,
      "file_name": "autofix_coordinator.py",
      "function_name": "AutofixCoordinator::_parse_single_hook_result",
      "path": "autofix_coordinator.py"
    },
    {
      "complexity": 3,
      "file_name": "autofix_coordinator.py",
      "function_name": "AutofixCoordinator::_parse_single_local_link_line",
      "path": "autofix_coordinator.py"
    },
    {
      "complexity": 3,
      "file_name": "autofix_coordinator.py",
      "function_name": "AutofixCoordinator::_run_in_threaded_loop",
      "path": "autofix_coordinator.py"
    },
    {
      "complexity": 3,
      "file_name": "autofix_coordinator.py",
      "function_name": "AutofixCoordinator::_should_skip_autofix",
      "path": "autofix_coordinator.py"
    },
    {
      "complexity": 4,
      "file_name": "autofix_coordinator.py",
      "function_name": "AutofixCoordinator::_detect_package_directory",
      "path": "autofix_coordinator.py"
    },
    {
      "complexity": 4,
      "file_name": "autofix_coordinator.py",
      "function_name": "AutofixCoordinator::_extract_process_output",
      "path": "autofix_coordinator.py"
    },
    {
      "complexity": 4,
      "file_name": "autofix_coordinator.py",
      "function_name": "AutofixCoordinator::_get_ruff_issue_type",
      "path": "autofix_coordinator.py"
    },
    {
      "complexity": 4,
      "file_name": "autofix_coordinator.py",
      "function_name": "AutofixCoordinator::_process_check_result",
      "path": "autofix_coordinator.py"
    },
    {
      "complexity": 4,
      "file_name": "autofix_coordinator.py",
      "function_name": "AutofixCoordinator::_should_parse_line",
      "path": "autofix_coordinator.py"
    },
    {
      "complexity": 4,
      "file_name": "autofix_coordinator.py",
      "function_name": "AutofixCoordinator::_validate_hook_result",
      "path": "autofix_coordinator.py"
    },
    {
      "complexity": 5,
      "file_name": "autofix_coordinator.py",
      "function_name": "AutofixCoordinator::_parse_check_local_links_output",
      "path": "autofix_coordinator.py"
    },
    {
      "complexity": 5,
      "file_name": "autofix_coordinator.py",
      "function_name": "AutofixCoordinator::_parse_codespell_output",
      "path": "autofix_coordinator.py"
    },
    {
      "complexity": 5,
      "file_name": "autofix_coordinator.py",
      "function_name": "AutofixCoordinator::_parse_type_checker_output",
      "path": "autofix_coordinator.py"
    },
    {
      "complexity": 5,
      "file_name": "autofix_coordinator.py",
      "function_name": "AutofixCoordinator::_process_fix_result",
      "path": "autofix_coordinator.py"
    },
    {
      "complexity": 5,
      "file_name": "autofix_coordinator.py",
      "function_name": "AutofixCoordinator::_validate_fix_command",
      "path": "autofix_coordinator.py"
    },
    {
      "complexity": 6,
      "file_name": "autofix_coordinator.py",
      "function_name": "AutofixCoordinator::_apply_comprehensive_stage_fixes",
      "path": "autofix_coordinator.py"
    },
    {
      "complexity": 6,
      "file_name": "autofix_coordinator.py",
      "function_name": "AutofixCoordinator::_parse_hook_results_to_issues",
      "path": "autofix_coordinator.py"
    },
    {
      "complexity": 6,
      "file_name": "autofix_coordinator.py",
      "function_name": "AutofixCoordinator::_parse_ruff_output",
      "path": "autofix_coordinator.py"
    },
    {
      "complexity": 6,
      "file_name": "autofix_coordinator.py",
      "function_name": "AutofixCoordinator::_should_stop_on_convergence",
      "path": "autofix_coordinator.py"
    },
    {
      "complexity": 7,
      "file_name": "autofix_coordinator.py",
      "function_name": "AutofixCoordinator::_extract_failed_hooks",
      "path": "autofix_coordinator.py"
    },
    {
      "complexity": 7,
      "file_name": "autofix_coordinator.py",
      "function_name": "AutofixCoordinator::apply_autofix_for_hooks",
      "path": "autofix_coordinator.py"
    },
    {
      "complexity": 8,
      "file_name": "autofix_coordinator.py",
      "function_name": "AutofixCoordinator::_handle_zero_issues_case",
      "path": "autofix_coordinator.py"
    },
    {
      "complexity": 8,
      "file_name": "autofix_coordinator.py",
      "function_name": "AutofixCoordinator::_parse_dead_code_output",
      "path": "autofix_coordinator.py"
    },
    {
      "complexity": 9,
      "file_name": "autofix_coordinator.py",
      "function_name": "AutofixCoordinator::_is_successful_fix",
      "path": "autofix_coordinator.py"
    },
    {
      "complexity": 9,
      "file_name": "autofix_coordinator.py",
      "function_name": "AutofixCoordinator::_parse_security_output",
      "path": "autofix_coordinator.py"
    },
    {
      "complexity": 11,
      "file_name": "autofix_coordinator.py",
      "function_name": "AutofixCoordinator::_parse_hook_to_issues",
      "path": "autofix_coordinator.py"
    },
    {
      "complexity": 12,
      "file_name": "autofix_coordinator.py",
      "function_name": "AutofixCoordinator::_apply_ai_agent_fixes",
      "path": "autofix_coordinator.py"
    },
    {
      "complexity": 12,
      "file_name": "autofix_coordinator.py",
      "function_name": "AutofixCoordinator::_parse_ruff_format_output",
      "path": "autofix_coordinator.py"
    },
    {
      "complexity": 14,
      "file_name": "autofix_coordinator.py",
      "function_name": "AutofixCoordinator::_parse_complexity_output",
      "path": "autofix_coordinator.py"
    },
    {
      "complexity": 15,
      "file_name": "autofix_coordinator.py",
      "function_name": "AutofixCoordinator::_parse_refurb_output",
      "path": "autofix_coordinator.py"
    }
  ],
  "targets": [
    "/Users/les/Projects/crackerjack/crackerjack/agents/documentation_agent.py",
    "/Users/les/Projects/crackerjack/crackerjack/core/autofix_coordinator.py"
  ]
}